monaco_dict_utils/__init__.py
monaco_dict_utils/params_to_sim.py
monaco_dict_utils/sim_factory.py
monaco_dict_utils-0.1.0.dist-info/licenses/LICENSE.txt
monaco_dict_utils-0.1.0.dist-info/METADATA
monaco_dict_utils-0.1.0.dist-info/WHEEL
monaco_dict_utils-0.1.0.dist-info/top_level.txt
monaco_dict_utils-0.1.0.dist-info/RECORD
