Metadata-Version: 2.4
Name: monaco-dict-utils
Version: 0.1.0
Summary: Easily bootstrap Monaco Monte Carlo simulations with a dictionary based workflow.
Author-email: Harold Martin <Harold.Martin@gmail.com>
License-Expression: MIT
Keywords: monaco,Monte Carlo,Monte Carlo methods,Monte Carlo simulation,data analysis
Classifier: Development Status :: 4 - Beta
Classifier: Intended Audience :: End Users/Desktop
Classifier: Intended Audience :: Science/Research
Classifier: Programming Language :: Python :: 3.13
Requires-Python: >=3.11
License-File: LICENSE.txt
Requires-Dist: monaco>=0.16.0
Dynamic: license-file
